geminitools/__init__.py
geminitools/endpoints.py
geminitools/gem.py
geminitools/utils.py
geminitools/tests/__init__.py
geminitools/tests/test_gem.py
geminitools-0.0.2.dist-info/LICENSE
geminitools-0.0.2.dist-info/METADATA
geminitools-0.0.2.dist-info/WHEEL
geminitools-0.0.2.dist-info/top_level.txt
geminitools-0.0.2.dist-info/RECORD
