Metadata-Version: 2.1
Name: geminitools
Version: 0.0.2
Summary: Talk to the Gemini Exchange API
Home-page: https://github.com/dlever/gemini-tools
Author: dlever
Author-email: dlever2021@protonmail.com
License: UNKNOWN
Project-URL: Bug Tracker, https://github.com/dlever/gemini-tools/issues
Platform: UNKNOWN
Classifier: Programming Language :: Python :: 3
Classifier: License :: OSI Approved :: GNU General Public License v3 (GPLv3)
Classifier: Operating System :: OS Independent
Requires-Python: >=3.8
Requires-Dist: requests
